odoo/addons/product_multi_barcode/README.rst
odoo/addons/product_multi_barcode/__init__.py
odoo/addons/product_multi_barcode/__manifest__.py
odoo/addons/product_multi_barcode/hooks.py
odoo/addons/product_multi_barcode/i18n/am.po
odoo/addons/product_multi_barcode/i18n/ar.po
odoo/addons/product_multi_barcode/i18n/bg.po
odoo/addons/product_multi_barcode/i18n/bs.po
odoo/addons/product_multi_barcode/i18n/ca.po
odoo/addons/product_multi_barcode/i18n/ca_ES.po
odoo/addons/product_multi_barcode/i18n/cs.po
odoo/addons/product_multi_barcode/i18n/da.po
odoo/addons/product_multi_barcode/i18n/da_DK.po
odoo/addons/product_multi_barcode/i18n/de.po
odoo/addons/product_multi_barcode/i18n/el_GR.po
odoo/addons/product_multi_barcode/i18n/en_GB.po
odoo/addons/product_multi_barcode/i18n/es.po
odoo/addons/product_multi_barcode/i18n/es_AR.po
odoo/addons/product_multi_barcode/i18n/es_CO.po
odoo/addons/product_multi_barcode/i18n/es_CR.po
odoo/addons/product_multi_barcode/i18n/es_EC.po
odoo/addons/product_multi_barcode/i18n/es_ES.po
odoo/addons/product_multi_barcode/i18n/es_MX.po
odoo/addons/product_multi_barcode/i18n/es_PE.po
odoo/addons/product_multi_barcode/i18n/es_PY.po
odoo/addons/product_multi_barcode/i18n/es_VE.po
odoo/addons/product_multi_barcode/i18n/eu.po
odoo/addons/product_multi_barcode/i18n/fa.po
odoo/addons/product_multi_barcode/i18n/fi.po
odoo/addons/product_multi_barcode/i18n/fr.po
odoo/addons/product_multi_barcode/i18n/fr_CA.po
odoo/addons/product_multi_barcode/i18n/fr_CH.po
odoo/addons/product_multi_barcode/i18n/fr_FR.po
odoo/addons/product_multi_barcode/i18n/gl.po
odoo/addons/product_multi_barcode/i18n/gl_ES.po
odoo/addons/product_multi_barcode/i18n/he.po
odoo/addons/product_multi_barcode/i18n/hr.po
odoo/addons/product_multi_barcode/i18n/hr_HR.po
odoo/addons/product_multi_barcode/i18n/it.po
odoo/addons/product_multi_barcode/i18n/ja.po
odoo/addons/product_multi_barcode/i18n/ko.po
odoo/addons/product_multi_barcode/i18n/lt.po
odoo/addons/product_multi_barcode/i18n/lt_LT.po
odoo13_addon_product_multi_barcode-13.0.1.1.0.dist-info/METADATA
odoo13_addon_product_multi_barcode-13.0.1.1.0.dist-info/WHEEL
odoo13_addon_product_multi_barcode-13.0.1.1.0.dist-info/top_level.txt
odoo13_addon_product_multi_barcode-13.0.1.1.0.dist-info/RECORD
